pyskim/__init__.py
pyskim/column_dispatch.py
pyskim/main.py
pyskim/text_formatter.py
pyskim/utils.py
pyskim-0.1.5.dist-info/LICENSE
pyskim-0.1.5.dist-info/METADATA
pyskim-0.1.5.dist-info/WHEEL
pyskim-0.1.5.dist-info/entry_points.txt
pyskim-0.1.5.dist-info/RECORD
