Metadata-Version: 2.1
Name: pyskim
Version: 0.1.5
Summary: Quickly create summary statistics for a given dataframe.
Home-page: https://github.com/kpj/pyskim
License: MIT
Author: kpj
Author-email: kim.philipp.jablonski@gmail.com
Requires-Python: >=3.10,<4.0
Classifier: License :: OSI Approved :: MIT License
Classifier: Programming Language :: Python :: 3
Classifier: Programming Language :: Python :: 3.10
Classifier: Programming Language :: Python :: 3.11
Classifier: Programming Language :: Python :: 3.12
Requires-Dist: click (>=8.1.7,<9.0.0)
Requires-Dist: ipython (>=8.21.0,<9.0.0)
Requires-Dist: numpy (>=1.26.4,<2.0.0)
Requires-Dist: pandas (>=2.2.0,<3.0.0)
Requires-Dist: scipy (>=1.12.0,<2.0.0)
Requires-Dist: tabulate (>=0.9.0,<0.10.0)
Project-URL: Repository, https://github.com/kpj/pyskim
